cellxgene_ontology_guide/__init__.py
cellxgene_ontology_guide/_constants.py
cellxgene_ontology_guide/curated_ontology_term_lists.py
cellxgene_ontology_guide/entities.py
cellxgene_ontology_guide/ontology_parser.py
cellxgene_ontology_guide/supported_versions.py
cellxgene_ontology_guide/data/CL-ontology-v2025-02-13.json.zst
cellxgene_ontology_guide/data/CL-ontology-v2025-04-10.json.zst
cellxgene_ontology_guide/data/CL-ontology-v2025-07-30.json.zst
cellxgene_ontology_guide/data/CVCL-ontology-53.0.json.zst
cellxgene_ontology_guide/data/EFO-ontology-v3.75.0.json.zst
cellxgene_ontology_guide/data/EFO-ontology-v3.78.0.json.zst
cellxgene_ontology_guide/data/EFO-ontology-v3.82.0.json.zst
cellxgene_ontology_guide/data/FBbt-ontology-v2025-02-13.json.zst
cellxgene_ontology_guide/data/FBbt-ontology-v2025-03-27.json.zst
cellxgene_ontology_guide/data/FBbt-ontology-v2025-08-07.json.zst
cellxgene_ontology_guide/data/FBdv-ontology-v2024-12-04.json.zst
cellxgene_ontology_guide/data/FBdv-ontology-v2025-02-12.json.zst
cellxgene_ontology_guide/data/FBdv-ontology-v2025-03-26.json.zst
cellxgene_ontology_guide/data/FBdv-ontology-v2025-05-29.json.zst
cellxgene_ontology_guide/data/HANCESTRO-ontology-3.0.json.zst
cellxgene_ontology_guide/data/HANCESTRO-ontology-v2025-04-01.json.zst
cellxgene_ontology_guide/data/HsapDv-ontology-v2025-01-23.json.zst
cellxgene_ontology_guide/data/MONDO-ontology-v2025-02-04.json.zst
cellxgene_ontology_guide/data/MONDO-ontology-v2025-05-06.json.zst
cellxgene_ontology_guide/data/MONDO-ontology-v2025-09-02.json.zst
cellxgene_ontology_guide/data/MmusDv-ontology-v2025-01-23.json.zst
cellxgene_ontology_guide/data/NCBITaxon-ontology-v2024-11-25.json.zst
cellxgene_ontology_guide/data/NCBITaxon-ontology-v2025-03-13.json.zst
cellxgene_ontology_guide/data/NCBITaxon-ontology-v2025-09-11.json.zst
cellxgene_ontology_guide/data/PATO-ontology-v2025-02-01.json.zst
cellxgene_ontology_guide/data/PATO-ontology-v2025-05-14.json.zst
cellxgene_ontology_guide-1.9.0.dist-info/licenses/LICENSE
cellxgene_ontology_guide-1.9.0.dist-info/METADATA
cellxgene_ontology_guide-1.9.0.dist-info/WHEEL
cellxgene_ontology_guide-1.9.0.dist-info/top_level.txt
cellxgene_ontology_guide-1.9.0.dist-info/RECORD
