Metadata-Version: 2.4
Name: cellxgene_ontology_guide
Version: 1.9.0
Summary: Access ontology metadata used by CZ cellxgene
Author-email: Chan Zuckerberg Initiative Foundation <cellxgene@chanzuckerberg.com>
License: MIT License
Project-URL: Documentation, https://chanzuckerberg.github.io/cellxgene-ontology-guide/cellxgene_ontology_guide.html
Project-URL: Repository, https://github.com/chanzuckerberg/cellxgene-ontology-guide.git
Project-URL: Issues, https://github.com/chanzuckerberg/cellxgene-ontology-guide/issues
Project-URL: Changelog, https://github.com/chanzuckerberg/cellxgene-ontology-guide/blob/main/api/python/CHANGELOG.md
Classifier: Development Status :: 4 - Beta
Classifier: Intended Audience :: Developers
Classifier: Topic :: Software Development :: Build Tools
Classifier: License :: OSI Approved :: MIT License
Classifier: Programming Language :: Python :: 3.10
Classifier: Programming Language :: Python :: 3.11
Classifier: Programming Language :: Python :: 3.12
Requires-Python: ~=3.10
License-File: LICENSE
Requires-Dist: semantic_version<3,>=2.10.0
Requires-Dist: zstandard<1,>=0.25.0
Provides-Extra: test
Requires-Dist: pytest; extra == "test"
Requires-Dist: coverage; extra == "test"
Requires-Dist: nbconvert; extra == "test"
Requires-Dist: jupyter; extra == "test"
Requires-Dist: nbformat>=5.10.4; extra == "test"
Provides-Extra: docs
Requires-Dist: pdoc; extra == "docs"
Dynamic: license-file
